simplemath/__init__.py
simplemath/operations/__init__.py
simplemath/operations/basic_operations.py
simplemath/utils/__init__.py
simplemath/utils/helpers.py
simplemath_luca-0.1.0.dist-info/METADATA
simplemath_luca-0.1.0.dist-info/WHEEL
simplemath_luca-0.1.0.dist-info/top_level.txt
simplemath_luca-0.1.0.dist-info/RECORD
