Metadata-Version: 2.1
Name: simplemath-luca
Version: 0.1.0
Summary: Um pacote simples de operações matemáticas
Home-page: https://github.com/seu_usuario/simplemath
Author: Luca
Author-email: luucadecastro@gmail.com
Classifier: Programming Language :: Python :: 3
Classifier: License :: OSI Approved :: MIT License
Classifier: Operating System :: OS Independent
Requires-Python: >=3.6
